vocodem/__init__.py
vocodem/helpers.py
vocodem/streaming/action/base_action.py
vocodem/streaming/action/factory.py
vocodem/streaming/action/nylas_send_email.py
vocodem/streaming/action/phone_call_action.py
vocodem/streaming/action/transfer_call.py
vocodem/streaming/action/utils.py
vocodem/streaming/action/worker.py
vocodem/streaming/agent/__init__.py
vocodem/streaming/agent/anthropic_agent.py
vocodem/streaming/agent/base_agent.py
vocodem/streaming/agent/bot_sentiment_analyser.py
vocodem/streaming/agent/chat_gpt_agent.py
vocodem/streaming/agent/echo_agent.py
vocodem/streaming/agent/factory.py
vocodem/streaming/agent/gpt4all_agent.py
vocodem/streaming/agent/gpt_summary_agent.py
vocodem/streaming/agent/information_retrieval_agent.py
vocodem/streaming/agent/llamacpp_agent.py
vocodem/streaming/agent/llm_agent.py
vocodem/streaming/agent/prompts/action_prompt.py
vocodem/streaming/agent/response_validator.py
vocodem/streaming/agent/restful_user_implemented_agent.py
vocodem/streaming/agent/utils.py
vocodem/streaming/agent/vertex_ai_agent.py
vocodem/streaming/agent/websocket_user_implemented_agent.py
vocodem/streaming/cache/openai-embeddings-fillers-cache.json
vocodem/streaming/cache/openai-embeddings-responses-cache.json
vocodem/streaming/client_backend/conversation.py
vocodem/streaming/constants.py
vocodem/streaming/hosted_streaming_conversation.py
vocodem/streaming/ignored_while_talking_fillers_fork.py
vocodem/streaming/input_device/base_input_device.py
vocodem/streaming/input_device/file_input_device.py
vocodem/streaming/input_device/microphone_input.py
vocodem/streaming/input_device/rnn_noise.py
vocodem/streaming/input_device/silero_vad.py
vocodem/streaming/input_device/stream_handler.py
vocodem/streaming/json_cache_proxy.py
vocodem/streaming/models/actions.py
vocodem/streaming/models/agent.py
vocodem/streaming/models/audio_encoding.py
vocodem/streaming/models/client_backend.py
vocodem/streaming/models/events.py
vocodem/streaming/models/message.py
vocodem-0.1.420.dist-info/LICENSE
vocodem-0.1.420.dist-info/METADATA
vocodem-0.1.420.dist-info/WHEEL
vocodem-0.1.420.dist-info/RECORD
